cosmic_ray/__init__.py
cosmic_ray/cli.py
cosmic_ray/config.py
cosmic_ray/exceptions.py
cosmic_ray/modules.py
cosmic_ray/mutating.py
cosmic_ray/plugins.py
cosmic_ray/progress.py
cosmic_ray/testing.py
cosmic_ray/timing.py
cosmic_ray/util.py
cosmic_ray/version.py
cosmic_ray/work_db.py
cosmic_ray/work_item.py
cosmic_ray/ast/__init__.py
cosmic_ray/ast/ast_query.py
cosmic_ray/commands/__init__.py
cosmic_ray/commands/execute.py
cosmic_ray/commands/init.py
cosmic_ray/commands/new_config.py
cosmic_ray/distribution/__init__.py
cosmic_ray/distribution/distributor.py
cosmic_ray/distribution/http.py
cosmic_ray/distribution/local.py
cosmic_ray/operators/__init__.py
cosmic_ray/operators/binary_operator_replacement.py
cosmic_ray/operators/boolean_replacer.py
cosmic_ray/operators/break_continue.py
cosmic_ray/operators/comparison_operator_replacement.py
cosmic_ray/operators/exception_replacer.py
cosmic_ray/operators/keyword_replacer.py
cosmic_ray/operators/no_op.py
cosmic_ray/operators/number_replacer.py
cosmic_ray/operators/operator.py
cosmic_ray/operators/provider.py
cosmic_ray/operators/remove_decorator.py
cosmic_ray/operators/unary_operator_replacement.py
cosmic_ray/operators/util.py
cosmic_ray/operators/variable_inserter.py
cosmic_ray/operators/variable_replacer.py
cosmic_ray/operators/zero_iteration_for_loop.py
cosmic_ray/tools/__init__.py
cosmic_ray/tools/badge.py
cosmic_ray/tools/html.py
cosmic_ray/tools/http_workers.py
cosmic_ray/tools/report.py
cosmic_ray/tools/survival_rate.py
cosmic_ray/tools/xml.py
cosmic_ray/tools/filters/__init__.py
cosmic_ray/tools/filters/filter_app.py
cosmic_ray/tools/filters/git.py
cosmic_ray/tools/filters/operators_filter.py
cosmic_ray/tools/filters/pragma_no_mutate.py
cosmic_ray-8.4.3.dist-info/licenses/LICENCE.txt
cosmic_ray-8.4.3.dist-info/METADATA
cosmic_ray-8.4.3.dist-info/WHEEL
cosmic_ray-8.4.3.dist-info/entry_points.txt
cosmic_ray-8.4.3.dist-info/top_level.txt
cosmic_ray-8.4.3.dist-info/RECORD
