Metadata-Version: 2.4
Name: cosmic_ray
Version: 8.4.3
Summary: Mutation testing
Author-email: Sixty North AS <austin@sixty-north.com>
License: Copyright (c) 2015-2017 Sixty North AS
Project-URL: repository, https://github.com/sixty-north/cosmic-ray
Classifier: Development Status :: 4 - Beta
Classifier: Environment :: Console
Classifier: Intended Audience :: Developers
Classifier: License :: OSI Approved :: MIT License
Classifier: Operating System :: OS Independent
Classifier: Programming Language :: Python
Classifier: Programming Language :: Python :: 3.9
Classifier: Programming Language :: Python :: 3.10
Classifier: Programming Language :: Python :: 3.11
Classifier: Programming Language :: Python :: 3.12
Classifier: Programming Language :: Python :: 3.13
Classifier: Topic :: Software Development :: Libraries :: Python Modules
Classifier: Topic :: Software Development :: Testing
Requires-Python: >=3.9
License-File: LICENCE.txt
Requires-Dist: aiohttp
Requires-Dist: anybadge
Requires-Dist: click
Requires-Dist: decorator
Requires-Dist: exit_codes
Requires-Dist: gitpython
Requires-Dist: parso
Requires-Dist: qprompt
Requires-Dist: rich
Requires-Dist: sqlalchemy
Requires-Dist: stevedore
Requires-Dist: toml
Requires-Dist: yattag
Dynamic: license-file
